{
  "stats": {
    "suites": 6,
    "tests": 5,
    "passes": 3,
    "pending": 0,
    "failures": 2,
    "start": "2021-08-17T09:45:04.368Z",
    "end": "2021-08-17T09:45:05.893Z",
    "duration": 1525
  },
  "tests": [
    {
      "title": "returns the customerName",
      "fullTitle": "Fix the Scope declare customerName to be bob in global scope returns the customerName",
      "file": "/home/jaybelieve/phase-1/phase-1-scope-lab/test/indexTest.js",
      "duration": 2,
      "currentRetry": 0,
      "speed": "fast",
      "err": {}
    },
    {
      "title": "modifies the customerName variable",
      "fullTitle": "Fix the Scope upperCaseCustomerName() modifies the customerName variable",
      "file": "/home/jaybelieve/phase-1/phase-1-scope-lab/test/indexTest.js",
      "duration": 0,
      "currentRetry": 0,
      "speed": "fast",
      "err": {}
    },
    {
      "title": "setBestCustomer",
      "fullTitle": "Fix the Scope setBestCustomer() setBestCustomer",
      "file": "/home/jaybelieve/phase-1/phase-1-scope-lab/test/indexTest.js",
      "duration": 1,
      "currentRetry": 0,
      "speed": "fast",
      "err": {}
    },
    {
      "title": "overwrites the best customer",
      "fullTitle": "Fix the Scope overwriteBestCustomer() overwrites the best customer",
      "file": "/home/jaybelieve/phase-1/phase-1-scope-lab/test/indexTest.js",
      "duration": 1,
      "currentRetry": 0,
      "err": {
        "stack": "ReferenceError: overwriteBestCustomer is not defined\n    at Context.<anonymous> (test/indexTest.js:29:7)\n    at processImmediate (node:internal/timers:464:21)",
        "message": "overwriteBestCustomer is not defined",
        "multiple": [
          {
            "multiple": "ReferenceError: overwriteBestCustomer is not defined"
          }
        ]
      }
    },
    {
      "title": "unsuccessfully tries to reassign the least favorite customer",
      "fullTitle": "Fix the Scope changeLeastFavoriteCustomer() unsuccessfully tries to reassign the least favorite customer",
      "file": "/home/jaybelieve/phase-1/phase-1-scope-lab/test/indexTest.js",
      "duration": 0,
      "currentRetry": 0,
      "err": {
        "stack": "ReferenceError: changeLeastFavoriteCustomer is not defined\n    at Context.<anonymous> (test/indexTest.js:37:14)\n    at processImmediate (node:internal/timers:464:21)",
        "message": "changeLeastFavoriteCustomer is not defined",
        "multiple": [
          {
            "multiple": "ReferenceError: changeLeastFavoriteCustomer is not defined"
          }
        ]
      }
    }
  ],
  "pending": [],
  "failures": [
    {
      "title": "overwrites the best customer",
      "fullTitle": "Fix the Scope overwriteBestCustomer() overwrites the best customer",
      "file": "/home/jaybelieve/phase-1/phase-1-scope-lab/test/indexTest.js",
      "duration": 1,
      "currentRetry": 0,
      "err": {
        "stack": "ReferenceError: overwriteBestCustomer is not defined\n    at Context.<anonymous> (test/indexTest.js:29:7)\n    at processImmediate (node:internal/timers:464:21)",
        "message": "overwriteBestCustomer is not defined",
        "multiple": [
          {
            "multiple": "ReferenceError: overwriteBestCustomer is not defined"
          }
        ]
      }
    },
    {
      "title": "unsuccessfully tries to reassign the least favorite customer",
      "fullTitle": "Fix the Scope changeLeastFavoriteCustomer() unsuccessfully tries to reassign the least favorite customer",
      "file": "/home/jaybelieve/phase-1/phase-1-scope-lab/test/indexTest.js",
      "duration": 0,
      "currentRetry": 0,
      "err": {
        "stack": "ReferenceError: changeLeastFavoriteCustomer is not defined\n    at Context.<anonymous> (test/indexTest.js:37:14)\n    at processImmediate (node:internal/timers:464:21)",
        "message": "changeLeastFavoriteCustomer is not defined",
        "multiple": [
          {
            "multiple": "ReferenceError: changeLeastFavoriteCustomer is not defined"
          }
        ]
      }
    }
  ],
  "passes": [
    {
      "title": "returns the customerName",
      "fullTitle": "Fix the Scope declare customerName to be bob in global scope returns the customerName",
      "file": "/home/jaybelieve/phase-1/phase-1-scope-lab/test/indexTest.js",
      "duration": 2,
      "currentRetry": 0,
      "speed": "fast",
      "err": {}
    },
    {
      "title": "modifies the customerName variable",
      "fullTitle": "Fix the Scope upperCaseCustomerName() modifies the customerName variable",
      "file": "/home/jaybelieve/phase-1/phase-1-scope-lab/test/indexTest.js",
      "duration": 0,
      "currentRetry": 0,
      "speed": "fast",
      "err": {}
    },
    {
      "title": "setBestCustomer",
      "fullTitle": "Fix the Scope setBestCustomer() setBestCustomer",
      "file": "/home/jaybelieve/phase-1/phase-1-scope-lab/test/indexTest.js",
      "duration": 1,
      "currentRetry": 0,
      "speed": "fast",
      "err": {}
    }
  ]
}